yaradb_client/__init__.py
yaradb_client/client.py
yaradb_client-0.1.4.dist-info/METADATA
yaradb_client-0.1.4.dist-info/WHEEL
yaradb_client-0.1.4.dist-info/licenses/LICENSE
yaradb_client-0.1.4.dist-info/RECORD
