Metadata-Version: 2.4
Name: yaradb-client
Version: 0.1.4
Summary: Official Python-client for YaraDB.
Project-URL: Homepage, https://github.com/illusiOxd/yaradb-client-py
Project-URL: Bug Tracker, https://github.com/illusiOxd/yaradb-client-py/issues
Project-URL: Source, https://github.com/illusiOxd/yaradb
Author-email: Tymofii Shchur <tymofiischur@gmail.com>
License: Copyright (c) 2025 Tymofii Shchur Viktorovych
License-File: LICENSE
Classifier: Development Status :: 4 - Beta
Classifier: Intended Audience :: Developers
Classifier: License :: OSI Approved :: MIT License
Classifier: Operating System :: OS Independent
Classifier: Programming Language :: Python :: 3
Classifier: Programming Language :: Python :: 3.8
Classifier: Programming Language :: Python :: 3.9
Classifier: Programming Language :: Python :: 3.10
Classifier: Programming Language :: Python :: 3.11
Classifier: Programming Language :: Python :: 3.12
Classifier: Topic :: Database
Requires-Python: >=3.8
Requires-Dist: requests>=2.20.0
